bencode/BTL.py
bencode/__init__.py
bencode/_bencode.c
bencode/_bencode.cp313-win_amd64.pyd
bencode/_bencode.pyi
bencode/_bencode.pyx
bencode/bencode.py
bencode/py.typed
bencode/sds.c
bencode/sds.h
bencode/sdsalloc.h
bencode/util.c
bencode/util.h
bencode/win32_portability.h
bencode/win32_types_hiredis.h
fast_bencode-1.1.8.dist-info/METADATA
fast_bencode-1.1.8.dist-info/WHEEL
fast_bencode-1.1.8.dist-info/top_level.txt
fast_bencode-1.1.8.dist-info/zip-safe
fast_bencode-1.1.8.dist-info/RECORD
